nrl/__init__.py
nrl/constants.py
nrl/typing.py
nrl/io/__init__.py
nrl/model/__init__.py
nrl/model/deepwalk.py
nrl/model/gat2vec.py
nrl/model/node2vec.py
nrl/model/util.py
nrl/model/word2vec.py
nrl/struct/__init__.py
nrl/walker/__init__.py
nrl/walker/utils.py
nrl/walker/walkers.py
nrl-0.0.1.dist-info/LICENSE
nrl-0.0.1.dist-info/METADATA
nrl-0.0.1.dist-info/WHEEL
nrl-0.0.1.dist-info/entry_points.txt
nrl-0.0.1.dist-info/top_level.txt
nrl-0.0.1.dist-info/RECORD
